zhenxun_db_client/__init__.py
zhenxun_db_client-0.1.2.dist-info/METADATA
zhenxun_db_client-0.1.2.dist-info/WHEEL
zhenxun_db_client-0.1.2.dist-info/RECORD
