Metadata-Version: 2.1
Name: zhenxun-db-client
Version: 0.1.2
Summary: 
Author: HibiKier
Author-email: 775757368@qq.com
Requires-Python: >=3.10,<4.0
Classifier: Programming Language :: Python :: 3
Classifier: Programming Language :: Python :: 3.10
Classifier: Programming Language :: Python :: 3.11
Classifier: Programming Language :: Python :: 3.12
Requires-Dist: nonebot2 (>=2.3.3,<3.0.0)
Requires-Dist: tortoise-orm (>=0.20.0,<0.21.0)
